README.md
setup.py
tsne_torch/__init__.py
tsne_torch/tsne_torch.py
tsne_torch.egg-info/PKG-INFO
tsne_torch.egg-info/SOURCES.txt
tsne_torch.egg-info/dependency_links.txt
tsne_torch.egg-info/requires.txt
tsne_torch.egg-info/top_level.txt